sendchamp/__init__.py
sendchamp/_http_client.py
sendchamp/constants.py
sendchamp/error.py
sendchamp/sendchamp.py
sendchamp/services/__init__.py
sendchamp/services/customer.py
sendchamp/services/email.py
sendchamp/services/sms.py
sendchamp/services/verification.py
sendchamp/services/voice.py
sendchamp/services/whatsapp.py
sendchamp_py-0.0.1.dist-info/METADATA
sendchamp_py-0.0.1.dist-info/WHEEL
sendchamp_py-0.0.1.dist-info/top_level.txt
sendchamp_py-0.0.1.dist-info/RECORD
