Metadata-Version: 2.1
Name: sendchamp-py
Version: 0.0.1
Summary: Sendchamp API wrapper
Home-page: https://github.com/keosariel/sendchamp-py
Author: Kenneth Gabriel
Author-email: kennethgabriel78@gmail.com
License: MIT
Keywords: python,sendchamp,httpx,client,wrapper
Platform: UNKNOWN
Classifier: Development Status :: 1 - Planning
Classifier: Intended Audience :: Developers
Classifier: Programming Language :: Python :: 3
Classifier: Operating System :: Unix
Classifier: Operating System :: MacOS :: MacOS X
Classifier: Operating System :: Microsoft :: Windows
Requires-Dist: httpx (==0.22.0)
Provides-Extra: dotenv
Requires-Dist: python-dotenv ; extra == 'dotenv'
